{
    "version": 10,
    "$schema": "https://cmake.org/cmake/help/latest/_downloads/3e2d73bff478d88a7de0de736ba5e361/schema.json",
    "configurePresets": [
        {
            "name": "birobot-teleop",
            "displayName": "BiRobotTeleop RelWithDebInfo",
            "inherits": [
                "relwithdebinfo"
            ],
            "cacheVariables": {
                "WITH_RHPS1": "ON",
                "WITH_HRP4": "ON",
                "WITH_Panda": "ON",
		"WITH_HUMAN": "ON"
            }
        }
    ],
    "buildPresets": [
        {
            "name": "birobot-teleop",
            "displayName": "BiRobotTeleop RelWithDebInfo",
            "configurePreset": "birobot-teleop",
            "configuration": "RelWithDebInfo",
            "targets": [
                "install"
            ]
        }
    ]
}
