{
    "version": 10,
    "$schema": "https://cmake.org/cmake/help/latest/_downloads/3e2d73bff478d88a7de0de736ba5e361/schema.json",
    "configurePresets": [
        {
            "name": "alix",
            "displayName": "Alix RelWithDebInfo (with tests)",
            "inherits": [
                "relwithdebinfo"
            ],
            "cacheVariables": {
                "WITH_ROS_SUPPORT": "ON",
                "BUILD_TESTING": "ON",
                "WITH_RHPS1": "ON"
            }
        }
    ],
    "buildPresets": [
        {
            "name": "alix",
            "displayName": "Alix RelWithDebInfo (with tests)",
            "configurePreset": "alix",
            "configuration": "RelWithDebInfo",
            "targets": [
                "install"
            ]
        }
    ]
}
